qsar_modi/__init__.py
qsar_modi/chem_utils.py
qsar_modi/modi.py
qsar_modi/modi_cli.py
qsar_modi/py.typed
qsar_modi-0.1.0.dist-info/AUTHORS.md
qsar_modi-0.1.0.dist-info/entry_points.txt
qsar_modi-0.1.0.dist-info/LICENSE
qsar_modi-0.1.0.dist-info/METADATA
qsar_modi-0.1.0.dist-info/WHEEL
qsar_modi-0.1.0.dist-info/RECORD
