Metadata-Version: 2.3
Name: qsar-modi
Version: 0.1.0
Summary: Package for calculating the Modelability Index (MODI) of a QSAR dataset
License: MIT
Author: James Wellnitz
Author-email: wellnitz.james@gmail.com
Maintainer: James Wellnitz
Maintainer-email: wellnitz.james@gmail.com
Requires-Python: >=3.11,<4.0
Classifier: License :: OSI Approved :: MIT License
Classifier: Natural Language :: English
Classifier: Operating System :: OS Independent
Classifier: Programming Language :: Python :: 3
Classifier: Programming Language :: Python :: 3.11
Classifier: Programming Language :: Python :: 3.12
Classifier: Programming Language :: Python :: 3.13
Requires-Dist: click (>=8.1.3,<9.0.0)
Requires-Dist: numpy (>=2.3.1,<2.4.0)
Requires-Dist: psutil (>=7.0.0,<8.0.0)
Requires-Dist: rdkit (>=2025.3.3,<2026.0.0)
Requires-Dist: scipy (>=1.15.3,<1.16.0)
Requires-Dist: tqdm (>=4.66.1,<5.0.0)
Project-URL: Repository, https://github.com/molecularmodelinglab/modi
